speech_detect/__init__.py
speech_detect/exceptions.py
speech_detect/rms_calculator.py
speech_detect/sd_types.py
speech_detect/speech_detect.py
speech_detect/vad_parser.py
speech_detect-0.3.0.dist-info/licenses/LICENSE
speech_detect-0.3.0.dist-info/METADATA
speech_detect-0.3.0.dist-info/WHEEL
speech_detect-0.3.0.dist-info/top_level.txt
speech_detect-0.3.0.dist-info/RECORD
