Metadata-Version: 2.4
Name: speech-detect
Version: 0.3.0
Summary: A Python library for detecting speech segments and non-speech gaps in audio/video files using FSMN-VAD-ONNX with streaming processing
License: MIT
Project-URL: Homepage, https://github.com/speech2srt/speech-detect
Project-URL: Repository, https://github.com/speech2srt/speech-detect
Project-URL: Issues, https://github.com/speech2srt/speech-detect/issues
Requires-Python: >=3.10
License-File: LICENSE
Requires-Dist: numpy>=1.26.4
Requires-Dist: funasr-onnx>=0.4.1
Requires-Dist: ffmpeg-audio>=0.3.0
Requires-Dist: jieba>=0.42.1
Requires-Dist: torch>=2.9.1
Dynamic: license-file
